LICENSE
MANIFEST.in
README.rst
pyproject.toml
setup.cfg
setup.py
django_drf_cms.egg-info/PKG-INFO
django_drf_cms.egg-info/SOURCES.txt
django_drf_cms.egg-info/dependency_links.txt
django_drf_cms.egg-info/requires.txt
django_drf_cms.egg-info/top_level.txt
drf_cms/__init__.py
drf_cms/admin.py
drf_cms/apps.py
drf_cms/forms.py
drf_cms/mixins.py
drf_cms/models.py
drf_cms/permissions.py
drf_cms/serializers.py
drf_cms/shortcuts.py
drf_cms/storage_backends.py
drf_cms/tests.py
drf_cms/translation.py
drf_cms/urls.py
drf_cms/views.py
drf_cms/migrations/0001_initial.py
drf_cms/migrations/__init__.py